elastic_sdk/__init__.py
elastic_sdk-0.0.2.dist-info/DESCRIPTION.rst
elastic_sdk-0.0.2.dist-info/METADATA
elastic_sdk-0.0.2.dist-info/RECORD
elastic_sdk-0.0.2.dist-info/WHEEL
elastic_sdk-0.0.2.dist-info/metadata.json
elastic_sdk-0.0.2.dist-info/top_level.txt
