Metadata-Version: 2.0
Name: elastic-sdk
Version: 0.0.2
Summary: Python SDK for Elasticsearch
Home-page: https://github.com/mongkok/elastic-sdk/
Author: mongkok
Author-email: dani.pyc@gmail.com
License: MIT
Platform: UNKNOWN
Classifier: Development Status :: 1 - Planning
Classifier: Environment :: Web Environment
Classifier: Intended Audience :: Developers
Classifier: License :: OSI Approved :: MIT License
Classifier: Operating System :: OS Independent
Classifier: Programming Language :: Python
Classifier: Programming Language :: Python :: 3
Classifier: Programming Language :: Python :: 3.5
Classifier: Programming Language :: Python :: 3.6
Requires-Dist: elasticsearch (>=5.4.0)
Requires-Dist: elasticsearch-dsl (>=5.3.0)
